blarg.py
django_blarg-0.1.4.dist-info/DESCRIPTION.rst
django_blarg-0.1.4.dist-info/METADATA
django_blarg-0.1.4.dist-info/pydist.json
django_blarg-0.1.4.dist-info/RECORD
django_blarg-0.1.4.dist-info/top_level.txt
django_blarg-0.1.4.dist-info/WHEEL
