Metadata-Version: 2.0
Name: django-blarg
Version: 0.1.4
Summary: Django 404 and 500 pages the blarg way.
Home-page: https://github.com/pydanny/django-blarg
Author: Daniel Greenfeld
Author-email: pydanny@gmail.com
License: BSD
Keywords: django-blarg
Platform: UNKNOWN
Classifier: Development Status :: 2 - Pre-Alpha
Classifier: Environment :: Web Environment
Classifier: Intended Audience :: Developers
Classifier: License :: OSI Approved :: BSD License
Classifier: Natural Language :: English
Classifier: Framework :: Django
Classifier: Programming Language :: Python :: 2
Classifier: Programming Language :: Python :: 2.6
Classifier: Programming Language :: Python :: 2.7
Classifier: Programming Language :: Python :: 3
Classifier: Programming Language :: Python :: 3.3
Requires-Dist: django (>=1.0)
